<?xml version="1.0" encoding="utf-8" ?>
<dwsync>
<file name="content1.html" server="192.168.2.11//raid/data/htdocs/" local="130214586713716873" remote="130224053510000000" />
<file name="content2.html" server="192.168.2.11//raid/data/htdocs/" local="130214586714066879" remote="130224053510000000" />
<file name="content1.html" server="192.168.2.102//home/pi/" local="130214586713716873" remote="130247022770000000" />
<file name="content2.html" server="192.168.2.102//home/pi/" local="130214586714066879" remote="130247022770000000" />
<file name="content1.html" server="192.168.2.51//home/pi/" local="130316144726203221" remote="130316145670000000" />
<file name="content2.html" server="192.168.2.51//home/pi/" local="130316144726303221" remote="130316145670000000" />
<file name="content1.html" server="192.168.2.52//home/pi/" local="130316144726203221" remote="130338245420000000" />
<file name="content2.html" server="192.168.2.52//home/pi/" local="130316144726303221" remote="130338245420000000" />
</dwsync>